{
  "version": "v1.0.0",
  "generated_at": "2026-06-13T00:00:00Z",
  "vertical": "fitness",
  "description": "AEO metadata for fitness studios",
  "schemas": {
    "local_business": {
      "@context": "https://schema.org",
      "@type": "HealthAndBeautyBusiness",
      "name": "{{ gym_name }}",
      "image": "{{ gym_logo }}",
      "description": "{{ gym_description }}",
      "url": "{{ site_url }}",
      "telephone": "{{ phone }}",
      "address": {
        "@type": "PostalAddress",
        "streetAddress": "{{ street }}",
        "addressLocality": "{{ city }}",
        "addressRegion": "{{ state }}",
        "postalCode": "{{ zip }}"
      },
      "areaServed": "{{ service_area }}",
      "amenityFeature": ["Weight Equipment", "Cardio Equipment", "Locker Rooms", "Showers"],
      "knowsAbout": ["Strength Training", "Cardio Fitness", "Group Classes", "Personal Training"]
    },
    "fitness_class": {
      "@context": "https://schema.org",
      "@type": "Event",
      "name": "{{ class_name }}",
      "description": "{{ class_description }}",
      "startDate": "{{ schedule_time }}",
      "duration": "PT{{ duration }}M",
      "location": {
        "@type": "Place",
        "name": "{{ gym_name }}",
        "address": {
          "@type": "PostalAddress",
          "streetAddress": "{{ street }}",
          "addressLocality": "{{ city }}"
        }
      },
      "organizer": {
        "@type": "Organization",
        "name": "{{ gym_name }}"
      },
      "instructor": {
        "@type": "Person",
        "name": "{{ trainer_name }}"
      },
      "offers": {
        "@type": "Offer",
        "price": "{{ class_price }}",
        "priceCurrency": "USD"
      }
    },
    "membership_offer": {
      "@context": "https://schema.org",
      "@type": "Offer",
      "name": "{{ membership_tier }}",
      "description": "{{ membership_description }}",
      "price": "{{ monthly_price }}",
      "priceCurrency": "USD",
      "priceValidUntil": "{{ offer_expiry }}",
      "availability": "InStock",
      "url": "{{ membership_url }}"
    },
    "faq": {
      "@context": "https://schema.org",
      "@type": "FAQPage",
      "mainEntity": [
        {
          "@type": "Question",
          "name": "Can I try a class for free?",
          "acceptedAnswer": {
            "@type": "Answer",
            "text": "Yes! We offer a free week trial for new members."
          }
        },
        {
          "@type": "Question",
          "name": "Do you offer childcare?",
          "acceptedAnswer": {
            "@type": "Answer",
            "text": "Yes, childcare is available during select class times."
          }
        }
      ]
    }
  },
  "expertise_signals": {
    "author_credentials": [
      "NASM, ACE, or ISSA certifications (trainers)",
      "CPR/AED certification",
      "Specialization in fitness modalities"
    ],
    "experience_markers": [
      "Trainer bios with certifications",
      "Member transformation stories",
      "Class variety and schedule consistency",
      "Testimonials from regular members"
    ],
    "trustworthiness_signals": [
      "Clear membership pricing",
      "Free trial or day pass available",
      "Member reviews on Google/Yelp",
      "Transparent cancellation policy",
      "Cleanliness and safety certifications"
    ]
  },
  "meta_tags": {
    "title": "{{ gym_name }} | Fitness Studio & Gym in {{ city }}, {{ state }}",
    "description": "{{ gym_name }} offers fitness classes, personal training, and memberships. Start your free trial today.",
    "keywords": ["gym near me", "fitness classes {{ city }}", "personal training"],
    "canonical": "{{ site_url }}"
  }
}
